pg_simple_wraper/__init__.py
pg_simple_wraper/pg_simple_wraper.py
pg_simple_wraper-0.0.1.dist-info/METADATA
pg_simple_wraper-0.0.1.dist-info/WHEEL
pg_simple_wraper-0.0.1.dist-info/licenses/LICENSE
pg_simple_wraper-0.0.1.dist-info/RECORD
